packmlpy/__init__.py
packmlpy/statemachine/__init__.py
packmlpy/statemachine/definitions.py
packmlpy/statemachine/PackMlStateMachine.py
packmlpy/statemachine/StateMachineBuilder.py
packmlpy-1.0.0.dist-info/LICENSE
packmlpy-1.0.0.dist-info/METADATA
packmlpy-1.0.0.dist-info/WHEEL
packmlpy-1.0.0.dist-info/RECORD
