Metadata-Version: 2.1
Name: packmlpy
Version: 1.0.0
Summary: A Python implementation of the state machine defined in PackML / ISA 88 / IEC 61512
Home-page: https://github.com/aljoshakoecher/PackMLpy
License: MIT
Keywords: StateMachine,PackML,ISA88,Finite State Machine,FSM
Author: Aljosha Koecher
Author-email: aljosha.koecher@hsu-hh.de
Requires-Python: >=3.11,<4.0
Classifier: Development Status :: 4 - Beta
Classifier: Intended Audience :: Developers
Classifier: License :: OSI Approved :: MIT License
Classifier: Programming Language :: Python :: 3
Classifier: Programming Language :: Python :: 3.11
Classifier: Programming Language :: Python :: 3.4
Classifier: Programming Language :: Python :: 3.5
Classifier: Programming Language :: Python :: 3.6
Classifier: Programming Language :: Python :: 3.7
Classifier: Programming Language :: Python :: 3.8
Classifier: Programming Language :: Python :: 3.9
Classifier: Topic :: Software Development :: Build Tools
Requires-Dist: transitions (>=0.9.2,<0.10.0)
Project-URL: Repository, https://github.com/aljoshakoecher/PackMLpy
